miss/__init__.py
miss/builtins.py
miss/collections.py
miss/datetime.py
miss/functools.py
miss/identity.py
miss/lazy.py
miss/list.py
miss/math.py
miss/namespace.py
miss/six.py
miss/str.py
miss-0.5.dist-info/DESCRIPTION.rst
miss-0.5.dist-info/METADATA
miss-0.5.dist-info/RECORD
miss-0.5.dist-info/WHEEL
miss-0.5.dist-info/metadata.json
miss-0.5.dist-info/top_level.txt
