Metadata-Version: 1.0
Name: miss
Version: 0.5
Summary: A collection of generic functions and classes
Home-page: https://github.com/Changaco/python-miss
Author: Changaco
Author-email: changaco@changaco.oy.lc
License: CC0
Platform: UNKNOWN
